youtubeCommunityAlarm/__init__.py
youtubeCommunityAlarm/crontab_register.py
youtubeCommunityAlarm/youtube_community.py
youtubeCommunityAlarm/youtube_community_alarm.py
youtubeCommunityAlarm/test/__init__.py
youtubeCommunityAlarm/test/test_youtube_community.py
youtube_community_alarm-0.0.4.dist-info/METADATA
youtube_community_alarm-0.0.4.dist-info/WHEEL
youtube_community_alarm-0.0.4.dist-info/top_level.txt
youtube_community_alarm-0.0.4.dist-info/RECORD
