Metadata-Version: 2.1
Name: youtube-community-alarm
Version: 0.0.4
Summary: youtube community alarm package
Home-page: https://github.com/SionByeon/YoutubeCommunityAlarm
Author: palace
Author-email: ufo3764@naver.com
Requires-Python: >=3.6
